doctr_labeler-0.2.0.dist-info/licenses/LICENSE
labeler/__init__.py
labeler/logger.py
labeler/py.typed
labeler/version.py
labeler/automation/__init__.py
labeler/automation/auto_labeler.py
labeler/automation/tight_box.py
labeler/cli/__init__.py
labeler/cli/main.py
labeler/components/__init__.py
labeler/components/draw_poly.py
labeler/components/polygon.py
labeler/utils/__init__.py
labeler/utils/data_utils.py
labeler/utils/hub_factory.py
labeler/views/__init__.py
labeler/views/canvas.py
labeler/views/gui.py
doctr_labeler-0.2.0.dist-info/METADATA
doctr_labeler-0.2.0.dist-info/WHEEL
doctr_labeler-0.2.0.dist-info/entry_points.txt
doctr_labeler-0.2.0.dist-info/top_level.txt
doctr_labeler-0.2.0.dist-info/zip-safe
doctr_labeler-0.2.0.dist-info/RECORD
