Metadata-Version: 2.4
Name: doctr-labeler
Version: 0.2.0
Summary: A Python package for labeling and annotating documents
Author-email: Felix Dittrich <felixdittrich92@gmail.com>
Maintainer: Felix Dittrich
License:                                  Apache License
Project-URL: repository, https://github.com/text2knowledge/docTR-Labeler
Project-URL: tracker, https://github.com/text2knowledge/docTR-Labeler/issues
Project-URL: changelog, https://github.com/text2knowledge/docTR-Labeler/releases
Keywords: OCR,document processing,labeling,annotation,docTR,OnnxTR
Classifier: Development Status :: 4 - Beta
Classifier: Intended Audience :: Developers
Classifier: Intended Audience :: Education
Classifier: Intended Audience :: Science/Research
Classifier: License :: OSI Approved :: Apache Software License
Classifier: Natural Language :: English
Classifier: Operating System :: OS Independent
Classifier: Programming Language :: Python :: 3
Classifier: Programming Language :: Python :: 3.10
Classifier: Programming Language :: Python :: 3.11
Classifier: Programming Language :: Python :: 3.12
Classifier: Topic :: Scientific/Engineering
Requires-Python: <4,>=3.10.0
License-File: LICENSE
Requires-Dist: numpy<3.0.0,>=1.16.0
Requires-Dist: opencv-python<5.0.0,>=4.5.0
Requires-Dist: Pillow>=9.2.0
Requires-Dist: tqdm>=4.30.0
Requires-Dist: huggingface-hub<1.0.0,>=0.23.0
Requires-Dist: sv-ttk>=2.6.0
Requires-Dist: darkdetect>=0.8.0
Requires-Dist: onnxtr[gpu]<1.0.0,>=0.6.0; sys_platform != "darwin"
Requires-Dist: onnxtr[cpu]<1.0.0,>=0.6.0; sys_platform == "darwin"
Provides-Extra: testing
Requires-Dist: pytest>=5.3.2; extra == "testing"
Requires-Dist: pytest-xvfb>=3.0.0; extra == "testing"
Requires-Dist: coverage[toml]>=4.5.4; extra == "testing"
Requires-Dist: requests>=2.20.0; extra == "testing"
Provides-Extra: quality
Requires-Dist: ruff>=0.1.5; extra == "quality"
Requires-Dist: mypy>=0.812; extra == "quality"
Requires-Dist: pre-commit>=2.17.0; extra == "quality"
Provides-Extra: dev
Requires-Dist: pytest>=5.3.2; extra == "dev"
Requires-Dist: pytest-xvfb>=3.0.0; extra == "dev"
Requires-Dist: coverage[toml]>=4.5.4; extra == "dev"
Requires-Dist: requests>=2.20.0; extra == "dev"
Requires-Dist: ruff>=0.1.5; extra == "dev"
Requires-Dist: mypy>=0.812; extra == "dev"
Requires-Dist: pre-commit>=2.17.0; extra == "dev"
Dynamic: license-file
